pyMetaClasses/__init__.py
pyMetaClasses-1.3.1.dist-info/LICENSE.md
pyMetaClasses-1.3.1.dist-info/METADATA
pyMetaClasses-1.3.1.dist-info/WHEEL
pyMetaClasses-1.3.1.dist-info/top_level.txt
pyMetaClasses-1.3.1.dist-info/RECORD
