Metadata-Version: 2.1
Name: pyMetaClasses
Version: 1.3.1
Summary: A collection of MetaClasses for Python.
Home-page: https://github.com/Paebbels/pyMetaClasses
Author: Patrick Lehmann
Author-email: Paebbels@gmail.com
License: UNKNOWN
Project-URL: Documentation, https://pyMetaClasses.readthedocs.io/en/latest/
Project-URL: Source Code, https://github.com/Paebbels/pyMetaClasses
Project-URL: Issue Tracker, https://github.com/Paebbels/pyMetaClasses/issues
Keywords: Python3 MetaClass Collection
Platform: UNKNOWN
Classifier: License :: OSI Approved :: Apache Software License
Classifier: Operating System :: OS Independent
Classifier: Programming Language :: Python :: 3 :: Only
Classifier: Programming Language :: Python :: 3.6
Classifier: Programming Language :: Python :: 3.7
Classifier: Programming Language :: Python :: 3.8
Classifier: Programming Language :: Python :: 3.9
Classifier: Development Status :: 5 - Production/Stable
Classifier: Intended Audience :: Developers
Classifier: Topic :: Utilities
Requires-Python: >=3.6
Requires-Dist: pydecor (>=2.0.1)
